chapman/__init__.py
chapman/_classes.py
chapman/_representation.py
chapman/base.py
chapman/constructions.py
chapman/examples.py
chapman/io.py
chapman/simulation.py
chapman/utilities.py
chapman_py-0.1.0.dist-info/LICENSE
chapman_py-0.1.0.dist-info/METADATA
chapman_py-0.1.0.dist-info/WHEEL
chapman_py-0.1.0.dist-info/top_level.txt
chapman_py-0.1.0.dist-info/RECORD
